{
  "uid" : "86317d83ca2885e",
  "name" : "WOPHierarchyValidationTest",
  "title" : "WOPHierarchyValidationTest",
  "time" : {
    "start" : 1558127622209,
    "stop" : 1558127623681,
    "duration" : 1472
  },
  "summary" : {
    "attachments" : 0,
    "steps" : 8
  },
  "failure" : null,
  "description" : null,
  "severity" : "NORMAL",
  "status" : "PASSED",
  "suite" : {
    "uid" : "76c8451e15d8d73e",
    "name" : "Suite : Test",
    "title" : "Suite : Test"
  },
  "steps" : [ {
    "name" : "logStep[Started reading data from Excel]",
    "title" : "Started reading data from Excel",
    "time" : {
      "start" : 1558127595624,
      "stop" : 1558127595624,
      "duration" : 0
    },
    "summary" : {
      "attachments" : 0,
      "steps" : 0
    },
    "status" : "PASSED",
    "attachments" : [ ],
    "steps" : [ ]
  }, {
    "name" : "logStep[Started reading data from Excel]",
    "title" : "Started reading data from Excel",
    "time" : {
      "start" : 1558127595809,
      "stop" : 1558127595809,
      "duration" : 0
    },
    "summary" : {
      "attachments" : 0,
      "steps" : 0
    },
    "status" : "PASSED",
    "attachments" : [ ],
    "steps" : [ ]
  }, {
    "name" : "logStep[Started reading data from Excel]",
    "title" : "Started reading data from Excel",
    "time" : {
      "start" : 1558127595955,
      "stop" : 1558127595956,
      "duration" : 1
    },
    "summary" : {
      "attachments" : 0,
      "steps" : 0
    },
    "status" : "PASSED",
    "attachments" : [ ],
    "steps" : [ ]
  }, {
    "name" : "logStep[Driver Loaded]",
    "title" : "Driver Loaded",
    "time" : {
      "start" : 1558127596094,
      "stop" : 1558127596094,
      "duration" : 0
    },
    "summary" : {
      "attachments" : 0,
      "steps" : 0
    },
    "status" : "PASSED",
    "attachments" : [ ],
    "steps" : [ ]
  }, {
    "name" : "logStep[Connected to the Database..]",
    "title" : "Connected to the Database..",
    "time" : {
      "start" : 1558127597844,
      "stop" : 1558127597844,
      "duration" : 0
    },
    "summary" : {
      "attachments" : 0,
      "steps" : 0
    },
    "status" : "PASSED",
    "attachments" : [ ],
    "steps" : [ ]
  }, {
    "name" : "logStep[Query executed successfully]",
    "title" : "Query executed successfully",
    "time" : {
      "start" : 1558127615025,
      "stop" : 1558127615025,
      "duration" : 0
    },
    "summary" : {
      "attachments" : 0,
      "steps" : 0
    },
    "status" : "PASSED",
    "attachments" : [ ],
    "steps" : [ ]
  }, {
    "name" : "logStep[Expected :AMCN.EVENT.WOP.CREATE.VERSIONS]",
    "title" : "Expected :AMCN.EVENT.WOP.CREATE.VERSIONS",
    "time" : {
      "start" : 1558127622225,
      "stop" : 1558127622225,
      "duration" : 0
    },
    "summary" : {
      "attachments" : 0,
      "steps" : 0
    },
    "status" : "PASSED",
    "attachments" : [ ],
    "steps" : [ ]
  }, {
    "name" : "logStep[Actual : AMCN.EVENT.WOP.CREATE.VERSIONS ]",
    "title" : "Actual : AMCN.EVENT.WOP.CREATE.VERSIONS ",
    "time" : {
      "start" : 1558127622225,
      "stop" : 1558127622225,
      "duration" : 0
    },
    "summary" : {
      "attachments" : 0,
      "steps" : 0
    },
    "status" : "PASSED",
    "attachments" : [ ],
    "steps" : [ ]
  } ],
  "attachments" : [ ],
  "issues" : [ ],
  "testIds" : [ ],
  "labels" : [ {
    "name" : "testSuite",
    "value" : "Suite"
  }, {
    "name" : "language",
    "value" : "JAVA"
  }, {
    "name" : "testGroup",
    "value" : "Test"
  }, {
    "name" : "testMethod",
    "value" : "WOPHierarchyValidationTest"
  }, {
    "name" : "feature",
    "value" : "CMSNV SMOKE"
  }, {
    "name" : "suite-name",
    "value" : "Suite : Test"
  }, {
    "name" : "story",
    "value" : "WOP ESB EVENTS"
  }, {
    "name" : "framework",
    "value" : "TestNG"
  }, {
    "name" : "suite-title",
    "value" : "Suite : Test"
  }, {
    "name" : "host",
    "value" : "MONO-HYD-LAP-41"
  }, {
    "name" : "thread",
    "value" : "24024@MONO-HYD-LAP-41.main(1)"
  }, {
    "name" : "testClass",
    "value" : "com.runner.test.TestEvents"
  } ],
  "parameters" : [ ]
}